skit_fixdf/__init__.py
skit_fixdf/cli.py
skit_fixdf/constants.py
skit_fixdf/fix/__init__.py
skit_fixdf/fix/calls_df.py
skit_fixdf/fix/datetime.py
skit_fixdf/fix/df.py
skit_fixdf/fix/labels_df.py
skit_fixdf/utils.py
skit_fixdf-0.1.12.dist-info/entry_points.txt
skit_fixdf-0.1.12.dist-info/LICENSE
skit_fixdf-0.1.12.dist-info/WHEEL
skit_fixdf-0.1.12.dist-info/METADATA
skit_fixdf-0.1.12.dist-info/RECORD
